MANIFEST.in
README.md
jana-widget.json
setup.cfg
setup.py
jana_widget/__init__.py
jana_widget/_version.py
jana_widget/example.py
jana_widget.egg-info/PKG-INFO
jana_widget.egg-info/SOURCES.txt
jana_widget.egg-info/dependency_links.txt
jana_widget.egg-info/not-zip-safe
jana_widget.egg-info/requires.txt
jana_widget.egg-info/top_level.txt
jana_widget/static/extension.js
jana_widget/static/index.js
jana_widget/static/index.js.map
jana_widget/static/jana-widget.js
jana_widget/static/jana-widget.js.map